structflo/__init__.py
structflo/helloworld.py
structflo-0.1.0.dist-info/licenses/LICENSE
structflo-0.1.0.dist-info/METADATA
structflo-0.1.0.dist-info/WHEEL
structflo-0.1.0.dist-info/top_level.txt
structflo-0.1.0.dist-info/RECORD
