Metadata-Version: 2.4
Name: structflo
Version: 0.1.0
Summary: A simple hello-world library.
Author: Structflo Maintainers
License: MIT
Requires-Python: >=3.8
License-File: LICENSE
Dynamic: license-file
